[
  {
    "id": "katha-1-2-2",
    "scripture_name": "Katha Upanishad",
    "tradition": "Shruti",
    "book": "Katha Upanishad",
    "chapter": "1",
    "verse": "2.2",
    "section_title": "The good and the merely pleasant",
    "original_language": "sanskrit",
    "original_text": "sreyas ca preyas ca manusyam etah",
    "transliteration": "sreyas ca preyas ca manusyam etas tau samparitya vivinakti dhirah",
    "translation": "The good and the merely pleasant come to a person. The wise examine both and distinguish between them.",
    "commentary_summary": "A foundational lens for decisions where comfort and truth are not the same thing.",
    "themes": ["discernment", "duty", "clarity", "desire"],
    "life_topics": ["career", "relationships", "decision-making", "temptation"],
    "source_edition": "Curated app adaptation from public-domain translations",
    "editorial_confidence": "high"
  },
  {
    "id": "katha-1-3-3-9",
    "scripture_name": "Katha Upanishad",
    "tradition": "Shruti",
    "book": "Katha Upanishad",
    "chapter": "1",
    "verse": "3.3-9",
    "section_title": "The chariot teaching",
    "original_language": "sanskrit",
    "original_text": "atmanam rathinam viddhi sariram ratham eva tu",
    "transliteration": "atmanam rathinam viddhi sariram ratham eva tu buddhim tu sarathim viddhi manah pragraham eva ca",
    "translation": "Know the self as the rider, the body as the chariot, the intellect as the charioteer, and the mind as the reins.",
    "commentary_summary": "Describes inner life as governance, where senses, mind, and intellect must be aligned.",
    "themes": ["mind", "discipline", "self-knowledge", "clarity"],
    "life_topics": ["anxiety", "discipline", "impulse", "purpose"],
    "source_edition": "Curated app adaptation from public-domain translations",
    "editorial_confidence": "high"
  },
  {
    "id": "isa-1",
    "scripture_name": "Isha Upanishad",
    "tradition": "Shruti",
    "book": "Isha Upanishad",
    "verse": "1",
    "section_title": "Enjoy through renunciation",
    "original_language": "sanskrit",
    "original_text": "tena tyaktena bhunjitha",
    "transliteration": "isavasyam idam sarvam yat kinca jagatyam jagat tena tyaktena bhunjitha ma grdah kasyasvid dhanam",
    "translation": "All this is pervaded by the Lord. Enjoy through renunciation; do not grasp at what belongs to another.",
    "commentary_summary": "Reframes enjoyment as right relationship rather than possession and grasping.",
    "themes": ["renunciation", "contentment", "wealth", "detachment"],
    "life_topics": ["wealth", "comparison", "envy", "self-worth"],
    "source_edition": "Curated app adaptation from public-domain translations",
    "editorial_confidence": "high"
  },
  {
    "id": "mundaka-1-2-12",
    "scripture_name": "Mundaka Upanishad",
    "tradition": "Shruti",
    "book": "Mundaka Upanishad",
    "chapter": "1",
    "verse": "2.12",
    "section_title": "Seeking what is lasting",
    "original_language": "sanskrit",
    "original_text": "pariksya lokan karma-citan brahmano nirvedam ayat",
    "transliteration": "pariksya lokan karma-citan brahmano nirvedam ayan nasty akrtah krtena",
    "translation": "Having examined the worlds won by action, the wise person comes to see that the uncreated is not gained by the merely created.",
    "commentary_summary": "Points to the moment when outer achievement no longer answers the deeper question of meaning.",
    "themes": ["purpose", "self-knowledge", "detachment", "wisdom"],
    "life_topics": ["purpose", "career", "burnout", "meaning"],
    "source_edition": "Curated app adaptation from public-domain translations",
    "editorial_confidence": "medium"
  }
]
